multimodal_fusion/ctvlib.cpython-310-x86_64-linux-gnu.so
multimodal_fusion/__init__.py
multimodal_fusion/fusion.py
multimodal_fusion/utils.py
multimodal_fusion/pyreg.py
multimodal_fusion-0.6.0.dist-info/METADATA
multimodal_fusion-0.6.0.dist-info/RECORD
multimodal_fusion-0.6.0.dist-info/top_level.txt
multimodal_fusion-0.6.0.dist-info/WHEEL
multimodal_fusion-0.6.0.dist-info/licenses/LICENSE
