Metadata-Version: 2.1
Name: multimodal-fusion
Version: 0.6.0
Summary: Multi-Modal Electron Microscopy Data Fusion
Author-email: Jonathan Schwartz <jtschwar@gmail.com>
License: MIT License
Project-URL: Homepage, https://github.com/jtschwar/Multi-Modal-2D-Data-Fusion
Project-URL: Repository, https://github.com/jtschwar/Multi-Modal-2D-Data-Fusion.git
Project-URL: Issues, https://github.com/jtschwar/Multi-Modal-2D-Data-Fusion/issues
Classifier: Development Status :: 4 - Beta
Classifier: Intended Audience :: Science/Research
Classifier: Programming Language :: Python :: 3
Classifier: Programming Language :: Python :: 3.8
Classifier: Programming Language :: Python :: 3.9
Classifier: Programming Language :: Python :: 3.10
Classifier: Programming Language :: Python :: 3.11
Classifier: Programming Language :: Python :: 3.12
Classifier: Programming Language :: C++
Classifier: Topic :: Scientific/Engineering
Requires-Python: >=3.8
License-File: LICENSE
Requires-Dist: numpy
Requires-Dist: scipy
Requires-Dist: matplotlib
Requires-Dist: h5py
Requires-Dist: tqdm
